pq_dataset/__init__.py
pq_dataset/class_functions/__init__.py
pq_dataset/class_functions/pdq_clean_up_data.py
pq_dataset/dataset_handling/__init__.py
pq_dataset/dataset_handling/csv_vukvo.py
pq_dataset/dataset_handling/ds_functions.py
pq_dataset/dataset_handling/parquet.py
pq_dataset/dataset_handling/pd_clean_up_columns.py
pq_dataset/main.py
pq_dataset/pq_dataset.py
pq_dataset/pqd_functions/__init__.py
pq_dataset/pqd_functions/extract_calculated_from_report_spec.py
pq_dataset/pqd_functions/reduce_columns_based_on_input.py
pq_dataset/room_specific_config.py
pq_dataset/utils/__init__.py
pq_dataset/utils/InputFile.py
pq_dataset/utils/variable_overview.py
pq_dataset-1.4.7.dist-info/METADATA
pq_dataset-1.4.7.dist-info/WHEEL
pq_dataset-1.4.7.dist-info/RECORD
